LICENCE
README.md
setup.py
ServerGit/__init__.py
ServerGit/server.py
ServerGit.egg-info/PKG-INFO
ServerGit.egg-info/SOURCES.txt
ServerGit.egg-info/dependency_links.txt
ServerGit.egg-info/requires.txt
ServerGit.egg-info/top_level.txt