Metadata-Version: 2.2
Name: ServerGit
Version: 0.0.2
Summary: Serve não oficial do GitHub!
Author: João Victor
Author-email: ajaxbytestudio@gmail.com
License: MIT License
Keywords: ServerGit
License-File: LICENCE
Requires-Dist: PyGithub
Requires-Dist: pandas
Dynamic: author
Dynamic: author-email
Dynamic: description
Dynamic: description-content-type
Dynamic: keywords
Dynamic: license
Dynamic: requires-dist
Dynamic: summary
